preoccupied/about.py
preoccupied-1.0.0.dist-info/LICENSE
preoccupied-1.0.0.dist-info/METADATA
preoccupied-1.0.0.dist-info/WHEEL
preoccupied-1.0.0.dist-info/top_level.txt
preoccupied-1.0.0.dist-info/RECORD
